mxm/config/__init__.py
mxm/config/_data/seeds/mxm.config/default.yaml
mxm/config/_data/seeds/mxm.config/environment.yaml
mxm/config/_data/seeds/mxm.config/local.yaml
mxm/config/_data/seeds/mxm.config/machine.yaml
mxm/config/_data/seeds/mxm.config/profile.yaml
mxm/config/_version.py
mxm/config/cli.py
mxm/config/helpers.py
mxm/config/ids.py
mxm/config/init_resolvers.py
mxm/config/initializer.py
mxm/config/installer.py
mxm/config/loader.py
mxm/config/py.typed
mxm/config/reports.py
mxm/config/resolver.py
mxm/config/types.py
mxm_config-0.5.1.dist-info/METADATA
mxm_config-0.5.1.dist-info/WHEEL
mxm_config-0.5.1.dist-info/entry_points.txt
mxm_config-0.5.1.dist-info/licenses/LICENSE
mxm_config-0.5.1.dist-info/RECORD
