Metadata-Version: 2.4
Name: mxm-config
Version: 0.5.1
Summary: MXM configuration loader and context resolver
License: MIT
License-File: LICENSE
Keywords: mxm,configuration,omegaconf,settings
Author: mxm
Author-email: contact@moneyexmachina.com
Requires-Python: >=3.12,<4.0
Classifier: Development Status :: 3 - Alpha
Classifier: License :: OSI Approved :: MIT License
Classifier: Programming Language :: Python :: 3
Classifier: Programming Language :: Python :: 3.12
Classifier: Programming Language :: Python :: 3.13
Classifier: Programming Language :: Python :: 3.14
Classifier: Programming Language :: Python :: 3 :: Only
Classifier: Typing :: Typed
Requires-Dist: click (>=8.1.6)
Requires-Dist: omegaconf (>=2.3.0,<3.0.0)
Requires-Dist: typer (>=0.16,<1.0)
Project-URL: Homepage, https://github.com/moneyexmachina/mxm-config
Project-URL: Issues, https://github.com/moneyexmachina/mxm-config/issues
Project-URL: Repository, https://github.com/moneyexmachina/mxm-config
